LICENSE
pycommons/__init__.py
pycommons/py.typed
pycommons/tests/__init__.py
pycommons/tests/case.py
pycommons/tests/condition.py
pycommons/tests/exception.py
pycommons/tests/matcher/__init__.py
pycommons/tests/matcher/matcher.py
pycommons/tests/parametrized.py
pycommons/tests/utils.py
pycommons_tests-0.0.2.dist-info/LICENSE
pycommons_tests-0.0.2.dist-info/METADATA
pycommons_tests-0.0.2.dist-info/WHEEL
pycommons_tests-0.0.2.dist-info/RECORD
