Metadata-Version: 2.1
Name: pycommons-tests
Version: 0.0.2
Summary: Python Commons Base
Home-page: https://github.com/pycommons/pycommons-tests
License: Apache-2.0
Author: Shashank Sharma
Author-email: shashankrnr32@gmail.com
Requires-Python: >=3.8,<4.0
Classifier: License :: OSI Approved :: Apache Software License
Classifier: Natural Language :: English
Classifier: Programming Language :: Python :: 3
Classifier: Programming Language :: Python :: 3.8
Classifier: Programming Language :: Python :: 3.9
Classifier: Programming Language :: Python :: 3.10
Classifier: Programming Language :: Python :: 3.11
Classifier: Programming Language :: Python :: 3.7
Requires-Dist: importlib_metadata
Requires-Dist: typing_extensions (==4.6.3)
